{
    "status": {
        "description": "Показывает текущее состояние бота и его время работы.",
        "aliases": [
            "status",
            "статус"
        ]
    },
    "dice": {
        "description": "Выбирает случайные числа для действий в диапазоне (по умолчанию 20).\nС помехой (`-` или `с помехой`) — минимум из двух бросков.\nС преимуществом (`+` или `с преимуществом`) — максимум из двух бросков.",
        "aliases": [
            "dice",
            "бросок",
            "кость",
            "к"
        ]
    },
    "chance": {
        "description": "Показывает вероятность выбранного события.",
        "aliases": [
            "chance",
            "вероятность",
            "инфа"
        ]
    },
    "magic8ball": {
        "description": "Отвечает на вопросы, как магический шар. Просто задайте вопрос, и получите случайный ответ.",
        "aliases": [
            "magic8ball",
            "шар",
            "магический шар"
        ]
    },
    "screenshot": {
        "wip": true,
        "description": "Создаёт скриншот пересланных сообщений. Аргументы: [от_пользователей] — указывает, делать ли снимки с точки зрения пользователей (true) или персонажей (false).",
        "aliases": [
            "screenshot",
            "скриншот",
            "снимок",
            "скрин"
        ]
    },
    "bugreport": {
        "description": "Отправляет отчет об ошибке. Вы можете как описать проблему, так и переслать сообщения, в которых она возникла.",
        "aliases": [
            "bugreport",
            "репорт",
            "баг"
        ]
    },
    "statistics": {
        "wip": true,
        "description": "Собирает статистику сообщений за последнюю неделю для каждого участника беседы, отображая количество сообщений и слов, формируя рейтинг участников.",
        "aliases": [
            "statistics",
            "статистика",
            "стат"
        ]
    },
    "who": {
    "description": "Случайным обрзаом выбирает участника для ответа на вопрос, а с аргументом 'я' расскажет, кто вы.",
    "aliases": [
        "who",
        "кто"
    ]},
    "help": {
    "description": "Выводит список доступных команд и их описание.\nИспользуйте 'help [команда]' для получения подробной информации о конкретной команде.",
    "aliases": [
        "help",
        "помощь",
        "хелп"
    ]
}

}